[{"@context":"https://schema.org","@type":"VideoObject","contentUrl":"https://cdn.pixabay.com/vimeo/267498461/heaven-15867.mp4?width=640&hash=ad8903b82ab63e50d8e138a91d600ee43932204c","thumbnailUrl":"https://i.vimeocdn.com/video/698036076-e94080e4099738ce921e7ee1631052591057fa54117d693677043238f42ad62f-d_640x360.jpg","name":"Heaven, Sunset","description":"Heaven, Sunset","license":"https://pixabay.com/service/license-summary/","acquireLicensePage":"/videos/heaven-sunset-15867/","duration":"T0M48S","uploadDate":"2024-02-12T07:03:54.110Z","sourceOrganization":{"@type":"Organization","name":"Pixabay"}}, {"@context":"https://schema.org","@type":"VideoObject","contentUrl":"https://cdn.pixabay.com/vimeo/367748189/apple-28122.mp4?width=640&hash=f70ed925f7a7b4867f3219a19ba531c8560f91f0","thumbnailUrl":"https://i.vimeocdn.com/video/824228957-ac8929703894ae6c3ff1a5a8710357d5b1a0855f9449c6122338ca8f3b664500-d_640x360.jpg","name":"Apple, Autumn, Blowing, Wind","description":"Apple, Autumn, Blowing, Wind, Twig In The Wind, Landscape","license":"https://pixabay.com/service/license-summary/","acquireLicensePage":"/videos/apple-autumn-blowing-wind-28122/","duration":"T0M38S","uploadDate":"2024-02-12T07:03:54.111Z","sourceOrganization":{"@type":"Organization","name":"Pixabay"}}, {"@context":"https://schema.org","@type":"VideoObject","contentUrl":"https://cdn.pixabay.com/vimeo/552236128/ducks-74462.mp4?width=640&hash=4d376f08a3a00783addbd8838a11400ffaa70137","thumbnailUrl":"https://i.vimeocdn.com/video/1140965392-822810262ff22018149666cf1569123d5a60fa0a1152502d7bf313d3a8c47651-d_640x360.jpg","name":"Ducks, Birds, Geese","description":"Ducks, Birds, Geese, Egyptian Ouette, Juvenile Ouette, Water","license":"https://pixabay.com/service/license-summary/","acquireLicensePage":"/videos/ducks-birds-geese-egyptian-ouette-74462/","duration":"T0M36S","uploadDate":"2024-02-12T07:03:54.112Z","sourceOrganization":{"@type":"Organization","name":"Pixabay"}}, {"@context":"https://schema.org","@type":"VideoObject","contentUrl":"https://cdn.pixabay.com/vimeo/523386889/corn-67773.mp4?width=1366&hash=7a02dd40a4a776abfcf80362dc8623b243d43771","thumbnailUrl":"https://i.vimeocdn.com/video/1084042269-05611ea9f8227072e2d7a2e14da59bd23146fad8d5018eed4bb4db3528dcdcc6-d_640x360.jpg","name":"Corn, Field, Green","description":"Corn, Field, Green, Agriculture, Wheat, Nature, Crops, Rural","license":"https://pixabay.com/service/license-summary/","acquireLicensePage":"/videos/corn-field-green-agriculture-wheat-67773/","duration":"T0M26S","uploadDate":"2024-02-12T07:03:54.113Z","sourceOrganization":{"@type":"Organization","name":"Pixabay"}}, {"@context":"https://schema.org","@type":"VideoObject","contentUrl":"https://cdn.pixabay.com/vimeo/210458758/swallow-8526.mp4?width=640&hash=b00894d738411f10e8087dc186118ad2ef7d2bbf","thumbnailUrl":"https://i.vimeocdn.com/video/626249460-32c045238a76e3011e1ef7aba16e068c54bc7ab3151138cc3744c1085582f289-d_640x360.jpg","name":"Swallow, Bird, Animal, Tame","description":"Swallow, Bird, Animal, Tame, Hand, Perched","license":"https://pixabay.com/service/license-summary/","acquireLicensePage":"/videos/swallow-bird-animal-tame-hand-8526/","duration":"T0M20S","uploadDate":"2024-02-12T07:03:54.115Z","sourceOrganization":{"@type":"Organization","name":"Pixabay"}}, {"@context":"https://schema.org","@type":"VideoObject","contentUrl":"https://cdn.pixabay.com/vimeo/558378014/caustics-76148.mp4?width=640&hash=6ec45525ee0e92243a2620c9d1b454017c5d6298","thumbnailUrl":"https://i.vimeocdn.com/video/1154033777-058df4a065d7f961940c515dc5f05a17a71486b4b2ee1912d9b998bc16ac10bd-d_640x360.jpg","name":"Caustics, Pattern, Water","description":"Caustics, Pattern, Water, Light Pattern, Light, Glow","license":"https://pixabay.com/service/license-summary/","acquireLicensePage":"/videos/caustics-pattern-water-76148/","duration":"T0M23S","uploadDate":"2024-02-12T07:03:54.116Z","sourceOrganization":{"@type":"Organization","name":"Pixabay"}}, {"@context":"https://schema.org","@type":"VideoObject","contentUrl":"https://cdn.pixabay.com/vimeo/377392939/abstract-29666.mp4?width=640&hash=b67d7f8a40d0c8e4999f763111c10e30248946b9","thumbnailUrl":"https://i.vimeocdn.com/video/836816317-ece697eb7b11dfe0e8ac13dddd90b6e326ecb66cea7b2246881c1234572752ed-d_640x360.jpg","name":"Abstract, To Dye, Shining","description":"Abstract, To Dye, Shining, Move, Film Leader, Film Credits","license":"https://pixabay.com/service/license-summary/","acquireLicensePage":"/videos/abstract-to-dye-shining-move-29666/","duration":"T0M52S","uploadDate":"2024-02-12T07:03:54.117Z","sourceOrganization":{"@type":"Organization","name":"Pixabay"}}, {"@context":"https://schema.org","@type":"VideoObject","contentUrl":"https://cdn.pixabay.com/vimeo/336506009/sea-23646.mp4?width=1280&hash=22a6f089f82190b6ecb15722b9bf600fa6c02914","thumbnailUrl":"https://i.vimeocdn.com/video/783365692-f33602255f59b9905b0f5d20d868a4e21b0405a5b3c03b5c7526c038180a0e67-d_640x360.jpg","name":"Sea, Marina, Ocean, That","description":"Sea, Marina, Ocean, That, Rocks, Stone, Maritime, Port","license":"https://pixabay.com/service/license-summary/","acquireLicensePage":"/videos/sea-marina-ocean-that-rocks-stone-23646/","duration":"T0M43S","uploadDate":"2024-02-12T07:03:54.118Z","sourceOrganization":{"@type":"Organization","name":"Pixabay"}}, {"@context":"https://schema.org","@type":"VideoObject","contentUrl":"https://cdn.pixabay.com/vimeo/182666883/cylinders-5087.mp4?width=640&hash=68e4cc7196b5814f55bfdcf24857bf498f61199d","thumbnailUrl":"https://i.vimeocdn.com/video/591641890-d2b4d4ee3513497107143f02c43deb911dcd0d6754a4daf9ff27ef9cf4c04c0d-d_640x360.jpg","name":"Cylinders, Beautiful Wallpaper","description":"Cylinders, Beautiful Wallpaper, Abstract, Circles, Objects","license":"https://pixabay.com/service/license-summary/","acquireLicensePage":"/videos/cylinders-abstract-circles-objects-5087/","duration":"T0M15S","uploadDate":"2024-02-12T07:03:54.119Z","sourceOrganization":{"@type":"Organization","name":"Pixabay"}}, {"@context":"https://schema.org","@type":"VideoObject","contentUrl":"https://cdn.pixabay.com/vimeo/402333394/moving-music-notes-34423.mp4?width=640&hash=f998e556e09917dddb615aab11db68924f83b157","thumbnailUrl":"https://i.vimeocdn.com/video/871393613-64258d72fafddfcd9dc39f9ea8c45e4b91ce7e5bb6fa0192ba1d1e24abfb536e-d_640x360.jpg","name":"Moving Music Notes, Music","description":"Moving Music Notes, Music, Musical, Notes, Movement","license":"https://pixabay.com/service/license-summary/","acquireLicensePage":"/videos/moving-music-notes-music-musical-34423/","duration":"T1M0S","uploadDate":"2024-02-12T07:03:54.120Z","sourceOrganization":{"@type":"Organization","name":"Pixabay"}}, {"@context":"https://schema.org","@type":"VideoObject","contentUrl":"https://cdn.pixabay.com/vimeo/383991394/bangkok-30945.mp4?width=640&hash=7bea41d7259c86c3c70d215535ea13e28cbaee6b","thumbnailUrl":"https://i.vimeocdn.com/video/845598125-f6ae33aca5d6f301f2c4ff82cc473ae6c596c968b561866b84beaaa3768dc750-d_640x360.jpg","name":"Bangkok, Thailand, City, Asia","description":"Bangkok, Thailand, City, Asia, Road, Traffic Jam, Traffic","license":"https://pixabay.com/service/license-summary/","acquireLicensePage":"/videos/bangkok-thailand-city-asia-road-30945/","duration":"T0M16S","uploadDate":"2024-02-12T07:03:54.121Z","sourceOrganization":{"@type":"Organization","name":"Pixabay"}}, {"@context":"https://schema.org","@type":"VideoObject","contentUrl":"https://cdn.pixabay.com/vimeo/154036057/tree-2053.mp4?width=640&hash=6c2b7f4c9a7fbf237dbec8012d57e621f4c594bc","thumbnailUrl":"https://i.vimeocdn.com/video/554483391-11eb883bfe2abecad70e91078f18160caa0fbf310c4a835ae0e33c849c7016a2-d_640x360.jpg","name":"Tree, Summer, Light, Leaf","description":"Tree, Summer, Light, Leaf, Green, Forest, Plant, Nature","license":"https://pixabay.com/service/license-summary/","acquireLicensePage":"/videos/tree-summer-light-leaf-green-2053/","duration":"T0M12S","uploadDate":"2024-02-12T07:03:54.123Z","sourceOrganization":{"@type":"Organization","name":"Pixabay"}}, {"@context":"https://schema.org","@type":"VideoObject","contentUrl":"https://cdn.pixabay.com/vimeo/402607072/beach-34513.mp4?width=640&hash=a667da25b9894a66e0a0ca52df658daff6779edd","thumbnailUrl":"https://i.vimeocdn.com/video/871772944-fff38dd7e3cc297356258f959b84bd9762dbf5944d9f0b950700e498dd81d593-d_640x360.jpg","name":"Beach, Coast, Relax, Run, Sand","description":"Beach, Coast, Relax, Run, Sand, Sea, Sport, Running, Annual","license":"https://pixabay.com/service/license-summary/","acquireLicensePage":"/videos/beach-coast-relax-run-sand-sea-34513/","duration":"T0M36S","uploadDate":"2024-02-12T07:03:54.124Z","sourceOrganization":{"@type":"Organization","name":"Pixabay"}}, {"@context":"https://schema.org","@type":"VideoObject","contentUrl":"https://cdn.pixabay.com/vimeo/504238656/swing-62362.mp4?width=1280&hash=5587ccad7bf87e29fc8a0bd4fb14937d1ff85e24","thumbnailUrl":"https://i.vimeocdn.com/video/1043443095-2412dee9b56b2ec5ffbc9591371f5b2d4eed57c3a69647876c63410ef0a301b1-d_640x360.jpg","name":"Swing, Tyre, Trees, Snow, Sun","description":"Swing, Tyre, Trees, Snow, Sun, Nature, Winter, Sparkles","license":"https://pixabay.com/service/license-summary/","acquireLicensePage":"/videos/swing-tyre-trees-snow-sun-nature-62362/","duration":"T0M17S","uploadDate":"2024-02-12T07:03:54.125Z","sourceOrganization":{"@type":"Organization","name":"Pixabay"}}, {"@context":"https://schema.org","@type":"VideoObject","contentUrl":"https://cdn.pixabay.com/vimeo/825301076/bird-162376.mp4?width=1280&hash=618e1e6b73fa7247009c217abb5f2c23dce5ac3c","thumbnailUrl":"https://i.vimeocdn.com/video/1667642204-7bdc83b9e1f904223e926229ce072389d5727cfc744c6d60d59be520a794279b-d_640x360.jpg","name":"Bird, Feeder, Avian","description":"Bird, Feeder, Avian, Ornithology, Scenery, Colombia","license":"https://pixabay.com/service/license-summary/","acquireLicensePage":"/videos/bird-feeder-avian-ornithology-162376/","duration":"T0M32S","uploadDate":"2024-02-12T07:03:54.126Z","sourceOrganization":{"@type":"Organization","name":"Pixabay"}}, {"@context":"https://schema.org","@type":"VideoObject","contentUrl":"https://cdn.pixabay.com/vimeo/460295808/river-50278.mp4?width=1280&hash=063d59441bcecaedd537cb91e1285c79e12126df","thumbnailUrl":"https://i.vimeocdn.com/video/961489253-4df667f66d25e9dbc6aa5a2531c69ad14b2f1092918c11e8f0b5e4bacf4f68a5-d_640x360.jpg","name":"River, Water, Environment","description":"River, Water, Environment, Forest, Horizon, Landscape","license":"https://pixabay.com/service/license-summary/","acquireLicensePage":"/videos/river-water-environment-forest-50278/","duration":"T0M18S","uploadDate":"2024-02-12T07:03:54.127Z","sourceOrganization":{"@type":"Organization","name":"Pixabay"}}, {"@context":"https://schema.org","@type":"VideoObject","contentUrl":"https://cdn.pixabay.com/vimeo/188704572/motorcycle-6098.mp4?width=640&hash=b62b3a118485be0503cb91c7f9784c0016fb6324","thumbnailUrl":"https://i.vimeocdn.com/video/598787796-fd0e767b956fa59a674e562ccf789d9c729cf72ac34ab3032e32c5ad64c2d6ba-d_640x360.jpg","name":"Motorcycle, City, Motorbike","description":"Motorcycle, City, Motorbike, Street, Road, Vehicle","license":"https://pixabay.com/service/license-summary/","acquireLicensePage":"/videos/motorcycle-city-motorbike-street-6098/","duration":"T0M13S","uploadDate":"2024-02-12T07:03:54.128Z","sourceOrganization":{"@type":"Organization","name":"Pixabay"}}, {"@context":"https://schema.org","@type":"VideoObject","contentUrl":"https://cdn.pixabay.com/vimeo/798856150/deimos-moon-150579.mp4?width=1280&hash=2547e09d472f60681d58100d85c3d977b8d46fa4","thumbnailUrl":"https://i.vimeocdn.com/video/1610687770-bfe00fb1de1dd0ca720b84aeb16e5a5a2a8a5181154a7d7709adcf8b769b918a-d_640x360.jpg","name":"Deimos Moon, Satellite, Mars","description":"Deimos Moon, Satellite, Mars, Moon","license":"https://pixabay.com/service/license-summary/","acquireLicensePage":"/videos/deimos-moon-satellite-mars-moon-150579/","duration":"T0M58S","uploadDate":"2024-02-12T07:03:54.129Z","sourceOrganization":{"@type":"Organization","name":"Pixabay"}}, {"@context":"https://schema.org","@type":"VideoObject","contentUrl":"https://cdn.pixabay.com/vimeo/241236706/globe-12653.mp4?width=640&hash=a2380b50fe025d6d4b591f77a3130a3d71fae58b","thumbnailUrl":"https://i.vimeocdn.com/video/664760059-7ca5a1734d0e7504ee42838ea2b3a5ae9645d5821d0c3fc09b855fad72b9a4cd-d_640x360.jpg","name":"Globe, 3D, 3D Model, Earth","description":"Globe, 3D, 3D Model, Earth, World, Geography, Education","license":"https://pixabay.com/service/license-summary/","acquireLicensePage":"/videos/globe-3d-3d-model-earth-world-12653/","duration":"T0M10S","uploadDate":"2024-02-12T07:03:54.130Z","sourceOrganization":{"@type":"Organization","name":"Pixabay"}}, {"@context":"https://schema.org","@type":"VideoObject","contentUrl":"https://cdn.pixabay.com/vimeo/365891030/black-and-white-27754.mp4?width=1280&hash=e8b9546144a8e5b13bc6f6798b61c1b52cda7366","thumbnailUrl":"https://i.vimeocdn.com/video/821759859-8a5483f15853efc750657bc780447ceb825358768150ba2e7a47ba49cf3c8c34-d_640x360.jpg","name":"Black And White, Clouds, Winds","description":"Black And White, Clouds, Winds, Cloudiness, Atmosphere","license":"https://pixabay.com/service/license-summary/","acquireLicensePage":"/videos/black-and-white-clouds-winds-27754/","duration":"T0M15S","uploadDate":"2024-02-12T07:03:54.132Z","sourceOrganization":{"@type":"Organization","name":"Pixabay"}}, {"@context":"https://schema.org","@type":"VideoObject","contentUrl":"https://cdn.pixabay.com/vimeo/440261045/torrent-44851.mp4?width=640&hash=755fe8ca6a010894db13693217427f694b9e81d6","thumbnailUrl":"https://i.vimeocdn.com/video/927609418-4ddb92d9336d8a75536e4fc888c69909390b4922c8b67d49ccc7ba36cd39a480-d_640x360.jpg","name":"Torrent, Water, Nature, Stream","description":"Torrent, Water, Nature, Stream, Outdoors, Rocks, Flow","license":"https://pixabay.com/service/license-summary/","acquireLicensePage":"/videos/torrent-water-nature-stream-44851/","duration":"T0M27S","uploadDate":"2024-02-12T07:03:54.133Z","sourceOrganization":{"@type":"Organization","name":"Pixabay"}}, {"@context":"https://schema.org","@type":"VideoObject","contentUrl":"https://cdn.pixabay.com/vimeo/409824173/macro-36426.mp4?width=640&hash=90bcbf0777c734966771b42f715bfa4b2c3d90b2","thumbnailUrl":"https://i.vimeocdn.com/video/881253173-4570e80fc2cb1b1ad53c038e4d9cb7a9daf34dc0b992b5c4cf1ac7a55c760b18-d_640x360.jpg","name":"Macro, Colours, Abstract","description":"Macro, Colours, Abstract, Pattern, Experimental, Psychedelic","license":"https://pixabay.com/service/license-summary/","acquireLicensePage":"/videos/macro-colours-abstract-pattern-36426/","duration":"T0M55S","uploadDate":"2024-02-12T07:03:54.134Z","sourceOrganization":{"@type":"Organization","name":"Pixabay"}}, {"@context":"https://schema.org","@type":"VideoObject","contentUrl":"https://cdn.pixabay.com/vimeo/135715309/flower-38.mp4?width=480&hash=d05d8f46896bfd7415a3213450f3b2a27d24ae0a","thumbnailUrl":"https://i.vimeocdn.com/video/529890309-dc75a017a8e99beb19db6b36ab4e8ddc87c6ed394835521355c9645ce086d0dd-d_640x360.jpg","name":"Flower, Yellow, Blossom","description":"Flower, Yellow, Blossom, Nature, Windy, Petals","license":"https://pixabay.com/service/license-summary/","acquireLicensePage":"/videos/flower-yellow-blossom-nature-windy-38/","duration":"T0M4S","uploadDate":"2024-02-12T07:03:54.135Z","sourceOrganization":{"@type":"Organization","name":"Pixabay"}}, {"@context":"https://schema.org","@type":"VideoObject","contentUrl":"https://cdn.pixabay.com/vimeo/715427087/bokeh-118640.mp4?width=1280&hash=d72d75de32746ed2718a325b1217ea638ce1cd47","thumbnailUrl":"https://i.vimeocdn.com/video/1441911602-4ef3fd1df9572176580676cf8c992cd619ab6a39c43e4b5702e2760835f9111f-d_640x360.jpg","name":"Bokeh, Lens Blur, Bokeh Effect","description":"Bokeh, Lens Blur, Bokeh Effect, After Effects","license":"https://pixabay.com/service/license-summary/","acquireLicensePage":"/videos/bokeh-lens-blur-bokeh-effect-118640/","duration":"T0M5S","uploadDate":"2024-02-12T07:03:54.136Z","sourceOrganization":{"@type":"Organization","name":"Pixabay"}}, {"@context":"https://schema.org","@type":"VideoObject","contentUrl":"https://cdn.pixabay.com/vimeo/643067633/frog-94232.mp4?width=640&hash=a3af23c66d4b87e1ff9ee43afe34122c5be3cbb8","thumbnailUrl":"https://i.vimeocdn.com/video/1293538667-839d08a5f44412ffdde0dee3a321b00b64d0e318eeeb3509a_640x360.jpg","name":"Frog, Amphibians, Creatures","description":"Frog, Amphibians, Creatures, Animal, Wild Animals, Fauna","license":"https://pixabay.com/service/license-summary/","acquireLicensePage":"/videos/frog-amphibians-creatures-animal-94232/","duration":"T0M15S","uploadDate":"2024-02-12T07:03:54.137Z","sourceOrganization":{"@type":"Organization","name":"Pixabay"}}, {"@context":"https://schema.org","@type":"VideoObject","contentUrl":"https://cdn.pixabay.com/vimeo/240358901/drone-12575.mp4?width=1280&hash=1e4fcc1e43c6e8fe03800231d07be0b106385f79","thumbnailUrl":"https://i.vimeocdn.com/video/663623838-d307e8b9bad96330236fca5aa1c07bf0e18c9d89e219b971170222a03a1ec6fb-d_640x360.jpg","name":"Drone, Aerial View, Heaven","description":"Drone, Aerial View, Heaven, Afterglow, Park, Flying","license":"https://pixabay.com/service/license-summary/","acquireLicensePage":"/videos/drone-aerial-view-heaven-afterglow-12575/","duration":"T0M6S","uploadDate":"2024-02-12T07:03:54.138Z","sourceOrganization":{"@type":"Organization","name":"Pixabay"}}, {"@context":"https://schema.org","@type":"VideoObject","contentUrl":"https://cdn.pixabay.com/vimeo/727221647/clouds-123259.mp4?width=640&hash=0842ad76f7d5e312157d3260ea553308b8aaa5c8","thumbnailUrl":"https://i.vimeocdn.com/video/1463969402-c30ea5d33006f79bac036ba76867bc9e13b92e3c0ef0ec7ece43693f933c0238-d_640x360.jpg","name":"Clouds, Wind, Nature, Colombia","description":"Clouds, Wind, Nature, Colombia","license":"https://pixabay.com/service/license-summary/","acquireLicensePage":"/videos/clouds-wind-nature-colombia-123259/","duration":"T0M21S","uploadDate":"2024-02-12T07:03:54.139Z","sourceOrganization":{"@type":"Organization","name":"Pixabay"}}, {"@context":"https://schema.org","@type":"VideoObject","contentUrl":"https://cdn.pixabay.com/vimeo/724719553/lamb-121733.mp4?width=640&hash=9aac73c352de6b8af3642587069e8348e898b50f","thumbnailUrl":"https://i.vimeocdn.com/video/1459169754-fff52414ec5f4db10fe243d30b0d95beb9546fada1b2bbe3c8d085cd78f534f0-d_640x360.jpg","name":"Lamb, Farm Animal, Sheep, Wool","description":"Lamb, Farm Animal, Sheep, Wool, Animals, Eating, Nature","license":"https://pixabay.com/service/license-summary/","acquireLicensePage":"/videos/lamb-farm-animal-sheep-wool-121733/","duration":"T1M20S","uploadDate":"2024-02-12T07:03:54.140Z","sourceOrganization":{"@type":"Organization","name":"Pixabay"}}, {"@context":"https://schema.org","@type":"VideoObject","contentUrl":"https://cdn.pixabay.com/vimeo/574618430/spheres-81312.mp4?width=640&hash=bd073c85a15e5319864612c4f58cc8890ef57630","thumbnailUrl":"https://i.vimeocdn.com/video/1188433528-d435790651cc85b5ec5b60b4b30581ff1230744957345586dbb059984c77b6f4-d_640x360.jpg","name":"Spheres, Pyramid, Portal","description":"Spheres, Pyramid, Portal, Geometry, Tetrahedron, Mystery, 3D","license":"https://pixabay.com/service/license-summary/","acquireLicensePage":"/videos/spheres-pyramid-portal-geometry-81312/","duration":"T0M36S","uploadDate":"2024-02-12T07:03:54.142Z","sourceOrganization":{"@type":"Organization","name":"Pixabay"}}, {"@context":"https://schema.org","@type":"VideoObject","contentUrl":"https://cdn.pixabay.com/vimeo/840291065/buildings-169070.mp4?width=1280&hash=351ab387d5b6eaf2d2ea9ac08f509977e7b86d46","thumbnailUrl":"https://i.vimeocdn.com/video/1690217390-b2e3e01c5cafed955440a9d9ef36de31cd683d5079376e25f15e9f9c1280e25f-d_640x360.jpg","name":"Buildings, Streets, Kiev","description":"Buildings, Streets, Kiev, Ukraine, Capital, Architecture","license":"https://pixabay.com/service/license-summary/","acquireLicensePage":"/videos/buildings-streets-kiev-ukraine-169070/","duration":"T0M23S","uploadDate":"2024-02-12T07:03:54.143Z","sourceOrganization":{"@type":"Organization","name":"Pixabay"}}, {"@context":"https://schema.org","@type":"VideoObject","contentUrl":"https://cdn.pixabay.com/vimeo/638414100/clouds-92916.mp4?width=1280&hash=111e4565a6ab3412064de77a491757242663fba0","thumbnailUrl":"https://i.vimeocdn.com/video/1283418687-94f8409bf7527880b29f8107f422ce6a96cc0adfecc0cb1bc_640x360.jpg","name":"Clouds, Cumulus, Heaven","description":"Clouds, Cumulus, Heaven, The Atmosphere, Wind, Weather","license":"https://pixabay.com/service/license-summary/","acquireLicensePage":"/videos/clouds-cumulus-heaven-92916/","duration":"T0M55S","uploadDate":"2024-02-12T07:03:54.144Z","sourceOrganization":{"@type":"Organization","name":"Pixabay"}}, {"@context":"https://schema.org","@type":"VideoObject","contentUrl":"https://cdn.pixabay.com/vimeo/738829424/house-127450.mp4?width=640&hash=2de47c8fd758eaeebbf6873ef02a10356dc3ab07","thumbnailUrl":"https://i.vimeocdn.com/video/1486658492-9de607f7a9dabd8a6194f885b13194dad1bf6aac9d571504d51d78d32a46908a-d_640x360.jpg","name":"House, Town, Ruined, Madeira","description":"House, Town, Ruined, Madeira, Madeira Island, Portugal","license":"https://pixabay.com/service/license-summary/","acquireLicensePage":"/videos/house-town-ruined-madeira-127450/","duration":"T0M33S","uploadDate":"2024-02-12T07:03:54.145Z","sourceOrganization":{"@type":"Organization","name":"Pixabay"}}, {"@context":"https://schema.org","@type":"VideoObject","contentUrl":"https://cdn.pixabay.com/vimeo/701051379/city-114510.mp4?width=1280&hash=29d7a628e03db7ed9ed87e0e0e0346d041d7dde3","thumbnailUrl":"https://i.vimeocdn.com/video/1416901925-1a8df29430af02cb57d9475e70b2a524f720b072bc92cb370b8e083316cad8c2-d_640x360.jpg","name":"City, Clouds, Storm, Colombia","description":"City, Clouds, Storm, Colombia","license":"https://pixabay.com/service/license-summary/","acquireLicensePage":"/videos/city-clouds-storm-colombia-114510/","duration":"T0M21S","uploadDate":"2024-02-12T07:03:54.146Z","sourceOrganization":{"@type":"Organization","name":"Pixabay"}}, {"@context":"https://schema.org","@type":"VideoObject","contentUrl":"https://cdn.pixabay.com/vimeo/796105855/snail-149421.mp4?width=1280&hash=d494ed2340d2fc9730ec6f944084337b5294755b","thumbnailUrl":"https://i.vimeocdn.com/video/1604009267-32892bf377bfb3cfe590bed3b1842ab740c9586010c3249db849dc11a011f56c-d_640x360.jpg","name":"Snail, Shell, Path, Slow","description":"Snail, Shell, Path, Slow, Forest, Trees, To Crawl, Animal","license":"https://pixabay.com/service/license-summary/","acquireLicensePage":"/videos/snail-shell-path-slow-forest-149421/","duration":"T0M52S","uploadDate":"2024-02-12T07:03:54.147Z","sourceOrganization":{"@type":"Organization","name":"Pixabay"}}, {"@context":"https://schema.org","@type":"VideoObject","contentUrl":"https://cdn.pixabay.com/vimeo/208181043/cow-8369.mp4?width=640&hash=5010669fc09728d9576fa0a97f407e00f1f8fe5e","thumbnailUrl":"https://i.vimeocdn.com/video/623434577-a856e9ba372b3ea45c5771ac3657df3e9568e6899811c60986eb6740869e19a4-d_640x360.jpg","name":"Cow, Animal, Agriculture, Farm","description":"Cow, Animal, Agriculture, Farm, Farming, Livestock, Milk","license":"https://pixabay.com/service/license-summary/","acquireLicensePage":"/videos/cow-animal-agriculture-farm-8369/","duration":"T0M9S","uploadDate":"2024-02-12T07:03:54.148Z","sourceOrganization":{"@type":"Organization","name":"Pixabay"}}, {"@context":"https://schema.org","@type":"VideoObject","contentUrl":"https://cdn.pixabay.com/vimeo/384511684/bird-31072.mp4?width=640&hash=cc8def26ec8c6527719bc38e8b171ee439387b05","thumbnailUrl":"https://i.vimeocdn.com/video/846285630-897055e3e3b0d1986a65a0f7ae6716a104fc2d7f9e7e93c2a6a336a61dc92129-d_640x360.jpg","name":"Bird, Dry Tree, Dove, Sky","description":"Bird, Dry Tree, Dove, Sky, Animal, Nature, Landscape","license":"https://pixabay.com/service/license-summary/","acquireLicensePage":"/videos/bird-dry-tree-dove-sky-animal-31072/","duration":"T0M19S","uploadDate":"2024-02-12T07:03:54.149Z","sourceOrganization":{"@type":"Organization","name":"Pixabay"}}, {"@context":"https://schema.org","@type":"VideoObject","contentUrl":"https://cdn.pixabay.com/vimeo/797862781/skulls-150067.mp4?width=640&hash=5c536307281c1a115fa26d0b9cddc0fa2732cc59","thumbnailUrl":"https://i.vimeocdn.com/video/1608065750-05d5af241e9665b3ac1463aaf1b6fdc5587f2dbf1ddc90abd5648d9bb06cbe6a-d_640x360.jpg","name":"Skulls, Fire Particles, Spooky","description":"Skulls, Fire Particles, Spooky, Scary, Night, Ghosts","license":"https://pixabay.com/service/license-summary/","acquireLicensePage":"/videos/skulls-fire-particles-spooky-scary-150067/","duration":"T0M6S","uploadDate":"2024-02-12T07:03:54.150Z","sourceOrganization":{"@type":"Organization","name":"Pixabay"}}, {"@context":"https://schema.org","@type":"VideoObject","contentUrl":"https://cdn.pixabay.com/vimeo/441206500/girl-44929.mp4?width=640&hash=813fb762834c87c0c8f5be4354552ff0756a177a","thumbnailUrl":"https://i.vimeocdn.com/video/929177800-61d3e4381aa56f29d888c6a418f1dd89c503767d5650fd6503642be3b5340efe-d_640x360.jpg","name":"Girl, Bicycle, Bike, Ride","description":"Girl, Bicycle, Bike, Ride, Exercise, Sports, Outdoor","license":"https://pixabay.com/service/license-summary/","acquireLicensePage":"/videos/girl-bicycle-bike-ride-exercise-44929/","duration":"T0M19S","uploadDate":"2024-02-12T07:03:54.151Z","sourceOrganization":{"@type":"Organization","name":"Pixabay"}}, {"@context":"https://schema.org","@type":"VideoObject","contentUrl":"https://cdn.pixabay.com/vimeo/585553872/earth-84590.mp4?width=640&hash=a27cccc1128f1e4a0b36b828e3bab2e9e4ea5205","thumbnailUrl":"https://i.vimeocdn.com/video/1211702562-8d43de61c497b9b22564408562cad060e34295f5c6842a394ccc160fa2067213-d_640x360.jpg","name":"Earth, Africa, Planet, World","description":"Earth, Africa, Planet, World, Continent, Globe, Geography","license":"https://pixabay.com/service/license-summary/","acquireLicensePage":"/videos/earth-africa-planet-world-84590/","duration":"T0M10S","uploadDate":"2024-02-12T07:03:54.152Z","sourceOrganization":{"@type":"Organization","name":"Pixabay"}}, {"@context":"https://schema.org","@type":"VideoObject","contentUrl":"https://cdn.pixabay.com/vimeo/659549520/christmas-dinner-101905.mp4?width=640&hash=01f9ee3ee8dbc3e51ebc72acba6e5ac6e5106f4b","thumbnailUrl":"https://i.vimeocdn.com/video/1332154474-ad6fa666fd3d4b0e1558fb35d1c87c77c5cc5adf4421cd0785f0684c00f65f59-d_640x360.jpg","name":"Christmas Dinner, Office","description":"Christmas Dinner, Office, Coworkers, Frame Christmas","license":"https://pixabay.com/service/license-summary/","acquireLicensePage":"/videos/christmas-dinner-office-coworkers-101905/","duration":"T0M27S","uploadDate":"2024-02-12T07:03:54.154Z","sourceOrganization":{"@type":"Organization","name":"Pixabay"}}, {"@context":"https://schema.org","@type":"VideoObject","contentUrl":"https://cdn.pixabay.com/vimeo/215588755/outlook-8808.mp4?width=640&hash=04c3ec40349e4de8c794def0a4390a0a6b035636","thumbnailUrl":"https://i.vimeocdn.com/video/632340504-045e245a230ab29ed01ce59ba95011fd8f4d96972de0390910932acb447bb58a-d_640x360.jpg","name":"Outlook, North Sea","description":"Outlook, North Sea, Cruise Ship, Sea, Fish Eye, Aida","license":"https://pixabay.com/service/license-summary/","acquireLicensePage":"/videos/outlook-north-sea-cruise-ship-sea-8808/","duration":"T0M20S","uploadDate":"2024-02-12T07:03:54.155Z","sourceOrganization":{"@type":"Organization","name":"Pixabay"}}, {"@context":"https://schema.org","@type":"VideoObject","contentUrl":"https://cdn.pixabay.com/vimeo/388997475/metro-31782.mp4?width=640&hash=68d333dd7ce0163b1dc31f8ba87be88ff4939f6b","thumbnailUrl":"https://i.vimeocdn.com/video/852500935-6900accf8102088385fd668cec109f61697258c08719272024e9d9ce3c4cdab8-d_640x360.jpg","name":"Metro, Bangkok, Thailand","description":"Metro, Bangkok, Thailand, Transport, People, Ticket","license":"https://pixabay.com/service/license-summary/","acquireLicensePage":"/videos/metro-bangkok-thailand-transport-31782/","duration":"T0M13S","uploadDate":"2024-02-12T07:03:54.156Z","sourceOrganization":{"@type":"Organization","name":"Pixabay"}}, {"@context":"https://schema.org","@type":"VideoObject","contentUrl":"https://cdn.pixabay.com/vimeo/472531785/river-53045.mp4?width=1280&hash=6bd1cdbba3ebb50281c24b347b66dcc239637c53","thumbnailUrl":"https://i.vimeocdn.com/video/982942777-ee3f0bcc806846f43dffa4f6fe01314df27c75bf76bacf90ea39fd15e0ef6a2d-d_640x360.jpg","name":"River, Green, Nature, Water","description":"River, Green, Nature, Water","license":"https://pixabay.com/service/license-summary/","acquireLicensePage":"/videos/river-green-nature-water-53045/","duration":"T1M0S","uploadDate":"2024-02-12T07:03:54.157Z","sourceOrganization":{"@type":"Organization","name":"Pixabay"}}, {"@context":"https://schema.org","@type":"VideoObject","contentUrl":"https://cdn.pixabay.com/vimeo/343454528/beach-24548.mp4?width=640&hash=9b92b48f86bb62c4127c5d20e0501033c674c6df","thumbnailUrl":"https://i.vimeocdn.com/video/792607093-b97317836e1e80a834290162f308f73b8233108edc15994dd92c8e6e9605b67d-d_640x360.jpg","name":"Beach, Florida, Tropical","description":"Beach, Florida, Tropical, Water, Sky, Travel, Tourism, Sand","license":"https://pixabay.com/service/license-summary/","acquireLicensePage":"/videos/beach-florida-tropical-water-sky-24548/","duration":"T0M9S","uploadDate":"2024-02-12T07:03:54.158Z","sourceOrganization":{"@type":"Organization","name":"Pixabay"}}, {"@context":"https://schema.org","@type":"VideoObject","contentUrl":"https://cdn.pixabay.com/vimeo/298307466/rainbow-18964.mp4?width=640&hash=90ee7607f04714915c685cf780c883cfe2ad7959","thumbnailUrl":"https://i.vimeocdn.com/video/736186187-644cfd3e656e4a4f8c516904ce5dc002d94130013a9aa6a377eb2051dac980f1-d_640x360.jpg","name":"Rainbow, Color Change","description":"Rainbow, Color Change, Abstract, Graphic, Digital, Lines","license":"https://pixabay.com/service/license-summary/","acquireLicensePage":"/videos/rainbow-color-change-abstract-18964/","duration":"T0M14S","uploadDate":"2024-02-12T07:03:54.159Z","sourceOrganization":{"@type":"Organization","name":"Pixabay"}}, {"@context":"https://schema.org","@type":"VideoObject","contentUrl":"https://cdn.pixabay.com/vimeo/459802180/forest-49795.mp4?width=640&hash=3dd242cb66842668f821913c99bf2c815e58926a","thumbnailUrl":"https://i.vimeocdn.com/video/960599560-cae7f5cc11a67356f1d6b3f9fdb5afa5886bb2946a30247d59c8ef467167c090-d_640x360.jpg","name":"Forest, Trees, Woods, Bridge","description":"Forest, Trees, Woods, Bridge, Nature, Path","license":"https://pixabay.com/service/license-summary/","acquireLicensePage":"/videos/forest-trees-woods-bridge-nature-49795/","duration":"T0M10S","uploadDate":"2024-02-12T07:03:54.160Z","sourceOrganization":{"@type":"Organization","name":"Pixabay"}}, {"@context":"https://schema.org","@type":"VideoObject","contentUrl":"https://cdn.pixabay.com/vimeo/411342268/little-girl-36542.mp4?width=640&hash=9b82ae65d4b1c9ac962276562de510c7e8cd8a69","thumbnailUrl":"https://i.vimeocdn.com/video/883337360-6d25ee9b86d9f4328d41dcaec3a68d58bd8b818875b21dc0472339e4fcc0a106-d_640x360.jpg","name":"Little Girl, Playing, Play","description":"Little Girl, Playing, Play, Toys, Colors","license":"https://pixabay.com/service/license-summary/","acquireLicensePage":"/videos/little-girl-playing-play-toys-36542/","duration":"T0M5S","uploadDate":"2024-02-12T07:03:54.161Z","sourceOrganization":{"@type":"Organization","name":"Pixabay"}}, {"@context":"https://schema.org","@type":"VideoObject","contentUrl":"https://cdn.pixabay.com/vimeo/555034939/ball-75244.mp4?width=640&hash=439c1cddc8adba9bf3bb3ef4e8583266da0421f4","thumbnailUrl":"https://i.vimeocdn.com/video/1147086603-616c0a959de0ca4b43d051cddaef2f4a92f9364dc1aad5e65c1fd2f67f47bbb5-d_640x360.jpg","name":"Ball, Football, Sports","description":"Ball, Football, Sports, Entertainment, Match","license":"https://pixabay.com/service/license-summary/","acquireLicensePage":"/videos/ball-football-sports-entertainment-75244/","duration":"T0M20S","uploadDate":"2024-02-12T07:03:54.162Z","sourceOrganization":{"@type":"Organization","name":"Pixabay"}}, {"@context":"https://schema.org","@type":"VideoObject","contentUrl":"https://cdn.pixabay.com/vimeo/460401364/bird-50336.mp4?width=640&hash=7ac370700f785989db186849e4b9ea88842b68b2","thumbnailUrl":"https://i.vimeocdn.com/video/961669876-7c95e6ab08b9d577a4c3a785307c8ad2302a12f13928b7feb605f898dd1a54f0-d_640x360.jpg","name":"Bird, Beak, Bill, Feathers","description":"Bird, Beak, Bill, Feathers, Plumage, Animal, Wild, Wildlife","license":"https://pixabay.com/service/license-summary/","acquireLicensePage":"/videos/bird-beak-bill-feathers-plumage-50336/","duration":"T0M12S","uploadDate":"2024-02-12T07:03:54.163Z","sourceOrganization":{"@type":"Organization","name":"Pixabay"}}, {"@context":"https://schema.org","@type":"VideoObject","contentUrl":"https://cdn.pixabay.com/vimeo/681143890/goats-108577.mp4?width=640&hash=090ada87a8ab830ea30bd51085638e5dc7af50ee","thumbnailUrl":"https://i.vimeocdn.com/video/1380652236-1d502449dfb97d1f4a395593ed39dd7a8a4eb4fb137cda4b382b4198b02377a3-d_640x360.jpg","name":"Goats, Herd, Farm, Livestock","description":"Goats, Herd, Farm, Livestock","license":"https://pixabay.com/service/license-summary/","acquireLicensePage":"/videos/goats-herd-farm-livestock-108577/","duration":"T0M19S","uploadDate":"2024-02-12T07:03:54.164Z","sourceOrganization":{"@type":"Organization","name":"Pixabay"}}, {"@context":"https://schema.org","@type":"VideoObject","contentUrl":"https://cdn.pixabay.com/vimeo/658819873/clover-100884.mp4?width=640&hash=ea7e2279c75f5806ddb1f92a90f4365674370084","thumbnailUrl":"https://i.vimeocdn.com/video/1330510237-c6b2fdbe66b6ac3f5bc88c27ea942f1ec80bdc8e11f449c4bb508dcfe5804bb0-d_640x360.jpg","name":"Clover, Plant, Leaf, Leaves","description":"Clover, Plant, Leaf, Leaves, Herb, Spring, Vascular Plant","license":"https://pixabay.com/service/license-summary/","acquireLicensePage":"/videos/clover-plant-leaf-leaves-herb-100884/","duration":"T0M15S","uploadDate":"2024-02-12T07:03:54.111Z","sourceOrganization":{"@type":"Organization","name":"Pixabay"}}, {"@context":"https://schema.org","@type":"VideoObject","contentUrl":"https://cdn.pixabay.com/vimeo/450995474/sunset-47125.mp4?width=640&hash=5f4a80f0980d3c53e1966217faadc67148d3780d","thumbnailUrl":"https://i.vimeocdn.com/video/945571599-f391d899bce356efbcc8ec6f057517b89fd5eb7a6d5dd7b7f2bf0e8bbbac03ab-d_640x360.jpg","name":"Sunset, Planet, Atmosphere","description":"Sunset, Planet, Atmosphere, Sky, Clouds, Fantasy, Twilight","license":"https://pixabay.com/service/license-summary/","acquireLicensePage":"/videos/sunset-planet-atmosphere-sky-47125/","duration":"T0M5S","uploadDate":"2024-02-12T07:03:54.112Z","sourceOrganization":{"@type":"Organization","name":"Pixabay"}}, {"@context":"https://schema.org","@type":"VideoObject","contentUrl":"https://cdn.pixabay.com/vimeo/405202859/telephone-34767.mp4?width=640&hash=8aca08e1cf26a3fdee48003906f9b2e545301bfe","thumbnailUrl":"https://i.vimeocdn.com/video/875284765-503089699baeecacedc8a52dba7418f8de65e9ee2eef0f74c922b1aedc0d6fad-d_640x360.jpg","name":"Telephone, Sound, Phone","description":"Telephone, Sound, Phone, Ringing, Call, Ring, Antique, Old","license":"https://pixabay.com/service/license-summary/","acquireLicensePage":"/videos/telephone-sound-phone-ringing-call-34767/","duration":"T0M17S","uploadDate":"2024-02-12T07:03:54.113Z","sourceOrganization":{"@type":"Organization","name":"Pixabay"}}, {"@context":"https://schema.org","@type":"VideoObject","contentUrl":"https://cdn.pixabay.com/vimeo/839220651/tractor-168401.mp4?width=1280&hash=c71cec5cf3715246fcb5302b116ba24d32de86ed","thumbnailUrl":"https://i.vimeocdn.com/video/1688553084-667907d9e8832647a0ac837618d4d178165dc417e7179ae97b01e3877cea135a-d_640x360.jpg","name":"Tractor, Grass, Farm","description":"Tractor, Grass, Farm, Agriculture, Austria, Styria","license":"https://pixabay.com/service/license-summary/","acquireLicensePage":"/videos/tractor-grass-farm-agriculture-168401/","duration":"T0M8S","uploadDate":"2024-02-12T07:03:54.114Z","sourceOrganization":{"@type":"Organization","name":"Pixabay"}}, {"@context":"https://schema.org","@type":"VideoObject","contentUrl":"https://cdn.pixabay.com/vimeo/656497213/frame-96724.mp4?width=640&hash=1092373fbf945a80f3fa824077f10771898502f5","thumbnailUrl":"https://i.vimeocdn.com/video/1325371141-390be1329531d78f4052b00188cec57d2f5f5f25f89bf408bd7c1fb64e3f1414-d_640x360.jpg","name":"Frame, Design, Business, Film","description":"Frame, Design, Business, Film, Graphic, Architecture, Office","license":"https://pixabay.com/service/license-summary/","acquireLicensePage":"/videos/frame-design-business-film-graphic-96724/","duration":"T0M15S","uploadDate":"2024-02-12T07:03:54.115Z","sourceOrganization":{"@type":"Organization","name":"Pixabay"}}, {"@context":"https://schema.org","@type":"VideoObject","contentUrl":"https://cdn.pixabay.com/vimeo/815765537/tank-157863.mp4?width=1280&hash=c2c43eee06430db29714ad2ffddd165881b483c0","thumbnailUrl":"https://i.vimeocdn.com/video/1650995460-535571b9d3f5c504226080390d288b4955ee9de0cfd9938a4100f1b5b18fd72d-d_640x360.jpg","name":"Tank, Armed Forces, Germany","description":"Tank, Armed Forces, Germany, Anti-Aircraft Tank, Cheetah","license":"https://pixabay.com/service/license-summary/","acquireLicensePage":"/videos/tank-armed-forces-germany-157863/","duration":"T0M8S","uploadDate":"2024-02-12T07:03:54.116Z","sourceOrganization":{"@type":"Organization","name":"Pixabay"}}, {"@context":"https://schema.org","@type":"VideoObject","contentUrl":"https://cdn.pixabay.com/vimeo/426189717/green-40727.mp4?width=640&hash=ce971748f7443c921fc829eceac13d662ba3429e","thumbnailUrl":"https://i.vimeocdn.com/video/904247553-580c5ad6de9947038a66c31fa9279ad294c621954c45b8db6038e4ed8ddbfb28-d_640x360.jpg","name":"Green, Wheat, Field","description":"Green, Wheat, Field, Agriculture, Nature, Plant, Food","license":"https://pixabay.com/service/license-summary/","acquireLicensePage":"/videos/green-wheat-field-agriculture-40727/","duration":"T0M32S","uploadDate":"2024-02-12T07:03:54.117Z","sourceOrganization":{"@type":"Organization","name":"Pixabay"}}, {"@context":"https://schema.org","@type":"VideoObject","contentUrl":"https://cdn.pixabay.com/vimeo/308335537/green-screen-20259.mp4?width=640&hash=871e90ef1d313bf1f525348a38becd28de6c9608","thumbnailUrl":"https://i.vimeocdn.com/video/748474302-d50a95483b944858b3b78f888b73fa06a73a6778322de749f8049ddbd7eea5a2-d_640x360.jpg","name":"Green Screen, 2019, 3D","description":"Green Screen, 2019, 3D, Youtube, Happy New Year, Business","license":"https://pixabay.com/service/license-summary/","acquireLicensePage":"/videos/green-screen-2019-3d-youtube-20259/","duration":"T0M12S","uploadDate":"2024-02-12T07:03:54.118Z","sourceOrganization":{"@type":"Organization","name":"Pixabay"}}, {"@context":"https://schema.org","@type":"VideoObject","contentUrl":"https://cdn.pixabay.com/vimeo/178898261/graphic-4437.mp4?width=640&hash=1641a178113978503979f57772450e734c4bb61c","thumbnailUrl":"https://i.vimeocdn.com/video/586648463-40571d35e1e20e40be667860b1cd82061f9554949f52eb7f4345d657bae0b77c-d_640x360.jpg","name":"Graphic, Beautiful Wallpaper","description":"Graphic, Beautiful Wallpaper, Rectangles, Move, Template","license":"https://pixabay.com/service/license-summary/","acquireLicensePage":"/videos/graphic-rectangles-move-template-4437/","duration":"T0M10S","uploadDate":"2024-02-12T07:03:54.120Z","sourceOrganization":{"@type":"Organization","name":"Pixabay"}}, {"@context":"https://schema.org","@type":"VideoObject","contentUrl":"https://cdn.pixabay.com/vimeo/439384665/fishing-44531.mp4?width=640&hash=21028bc069049efad42d530321ca960fc9441e31","thumbnailUrl":"https://i.vimeocdn.com/video/926065893-53c905940c6d0714428879827f189985a60e6cdec147fbb9b71f8658ff4cc705-d_640x360.jpg","name":"Fishing, Fish, Fisherman","description":"Fishing, Fish, Fisherman, Water, Animal, Angler, Blue","license":"https://pixabay.com/service/license-summary/","acquireLicensePage":"/videos/fishing-fish-fisherman-water-44531/","duration":"T0M12S","uploadDate":"2024-02-12T07:03:54.121Z","sourceOrganization":{"@type":"Organization","name":"Pixabay"}}, {"@context":"https://schema.org","@type":"VideoObject","contentUrl":"https://cdn.pixabay.com/vimeo/519813695/ocean-66676.mp4?width=1280&hash=851c4705a17eaa1118d56df006a34db4df90a56e","thumbnailUrl":"https://i.vimeocdn.com/video/1076477536-07c2064b29cb97ea03c897ac93cb35fc2a863f1fe54be4fabebcc7b792b9e873-d_640x360.jpg","name":"Ocean, Sunset, Horizon, Sea","description":"Ocean, Sunset, Horizon, Sea, Travel, Landscape, Beach","license":"https://pixabay.com/service/license-summary/","acquireLicensePage":"/videos/ocean-sunset-horizon-sea-travel-66676/","duration":"T0M29S","uploadDate":"2024-02-12T07:03:54.122Z","sourceOrganization":{"@type":"Organization","name":"Pixabay"}}, {"@context":"https://schema.org","@type":"VideoObject","contentUrl":"https://cdn.pixabay.com/vimeo/717336677/puerto-banus-119183.mp4?width=1280&hash=57089be8d287c0b80666a74dc744b8ca9bc98377","thumbnailUrl":"https://i.vimeocdn.com/video/1445449668-3b4ad0867fe5cb518dbc37274e5603760f0dd824306e8c6d62fe5a1bdd69763b-d_640x360.jpg","name":"Puerto Banus, Spain, By Night","description":"Puerto Banus, Spain, By Night, Aerial View, Bird&apos;S Eye View","license":"https://pixabay.com/service/license-summary/","acquireLicensePage":"/videos/puerto-banus-spain-by-night-119183/","duration":"T0M8S","uploadDate":"2024-02-12T07:03:54.123Z","sourceOrganization":{"@type":"Organization","name":"Pixabay"}}, {"@context":"https://schema.org","@type":"VideoObject","contentUrl":"https://cdn.pixabay.com/vimeo/797999325/ducks-150161.mp4?width=640&hash=fefd7821da271dc82ac50eb70d7bf941b7504f96","thumbnailUrl":"https://i.vimeocdn.com/video/1608528218-0d767b4769a7ec9cfb047c24e8e02a669253a799a22c855430b1a059ec11289a-d_640x360.jpg","name":"Ducks, Birds, Frozen Lake","description":"Ducks, Birds, Frozen Lake, Winter, Nature","license":"https://pixabay.com/service/license-summary/","acquireLicensePage":"/videos/ducks-birds-frozen-lake-winter-150161/","duration":"T0M42S","uploadDate":"2024-02-12T07:03:54.124Z","sourceOrganization":{"@type":"Organization","name":"Pixabay"}}, {"@context":"https://schema.org","@type":"VideoObject","contentUrl":"https://cdn.pixabay.com/vimeo/226983360/opel-gt-10947.mp4?width=1280&hash=36934df1af65959af93d6f20ea4a7a420fd08f21","thumbnailUrl":"https://i.vimeocdn.com/video/646736048-bd8de46fc522436786c3408b3f323f99bf3ee4bca1a3a579a713cc09e84f22bd-d_640x360.jpg","name":"Opel Gt, Airport, Plane","description":"Opel Gt, Airport, Plane, Aviation, Flying, Technology","license":"https://pixabay.com/service/license-summary/","acquireLicensePage":"/videos/opel-gt-airport-plane-aviation-10947/","duration":"T0M8S","uploadDate":"2024-02-12T07:03:54.125Z","sourceOrganization":{"@type":"Organization","name":"Pixabay"}}, {"@context":"https://schema.org","@type":"VideoObject","contentUrl":"https://cdn.pixabay.com/vimeo/282611622/giraffe-17513.mp4?width=640&hash=f34a9a08267814848b66a740e326e2272e4c3a80","thumbnailUrl":"https://i.vimeocdn.com/video/716692990-c0e4b4f7f5682566f2458d5b4bbbcdc6dac86cfd154aaafe84f5958f1e9cd28a-d_640x360.jpg","name":"Giraffe, Animal, Abstract","description":"Giraffe, Animal, Abstract, Pattern, Visuals, Loop","license":"https://pixabay.com/service/license-summary/","acquireLicensePage":"/videos/giraffe-animal-abstract-pattern-17513/","duration":"T0M30S","uploadDate":"2024-02-12T07:03:54.126Z","sourceOrganization":{"@type":"Organization","name":"Pixabay"}}, {"@context":"https://schema.org","@type":"VideoObject","contentUrl":"https://cdn.pixabay.com/vimeo/658807379/christmas-100171.mp4?width=640&hash=6558903f300889df602d32d3dbf5988f21532b53","thumbnailUrl":"https://i.vimeocdn.com/video/1330478164-456f20e9a9011d56fe1916459a37fbcdfe2263ef86314b44c4ef3b40c315a4d0-d_640x360.jpg","name":"Christmas, Holiday, Santa","description":"Christmas, Holiday, Santa, Merry, North Pole, Greeting","license":"https://pixabay.com/service/license-summary/","acquireLicensePage":"/videos/christmas-holiday-santa-merry-100171/","duration":"T0M20S","uploadDate":"2024-02-12T07:03:54.128Z","sourceOrganization":{"@type":"Organization","name":"Pixabay"}}, {"@context":"https://schema.org","@type":"VideoObject","contentUrl":"https://cdn.pixabay.com/vimeo/520787923/mountains-66453.mp4?width=640&hash=9dfd7ba59b5269bb136302c2e3e4097ed2745d21","thumbnailUrl":"https://i.vimeocdn.com/video/1078678106-665eb82241ffc71486b4f661075837b592a1e3b153dfa61cf27dc93860532986-d_640x360.jpg","name":"Mountains, Snow, Trees, Forest","description":"Mountains, Snow, Trees, Forest, Winter, Wintry","license":"https://pixabay.com/service/license-summary/","acquireLicensePage":"/videos/mountains-snow-trees-forest-winter-66453/","duration":"T0M10S","uploadDate":"2024-02-12T07:03:54.129Z","sourceOrganization":{"@type":"Organization","name":"Pixabay"}}, {"@context":"https://schema.org","@type":"VideoObject","contentUrl":"https://cdn.pixabay.com/vimeo/756991198/train-133517.mp4?width=1280&hash=7927c3ce191b5921fd9527eafeb69af38addab0e","thumbnailUrl":"https://i.vimeocdn.com/video/1520563105-e95fcc0a6ed727fd1a2b0b925a154999b01d6b25ac0226bb71b170a1a1abb072-d_640x360.jpg","name":"Train, Railway, Park, Drone","description":"Train, Railway, Park, Drone, Fly, Nature, Forest, Landscape","license":"https://pixabay.com/service/license-summary/","acquireLicensePage":"/videos/train-railway-park-drone-fly-133517/","duration":"T0M9S","uploadDate":"2024-02-12T07:03:54.130Z","sourceOrganization":{"@type":"Organization","name":"Pixabay"}}, {"@context":"https://schema.org","@type":"VideoObject","contentUrl":"https://cdn.pixabay.com/vimeo/725502788/waterfall-122459.mp4?width=1280&hash=db887d3df098fb98bcc9a97f1c5a2cad91cd46c1","thumbnailUrl":"https://i.vimeocdn.com/video/1460545761-016239eb944f434d9178e248a31c1fc610291f2947932c59ba84a6bc80b0d5f5-d_640x360.jpg","name":"Waterfall, Huibang Falls","description":"Waterfall, Huibang Falls, Water, Republic Of Korea, Korea","license":"https://pixabay.com/service/license-summary/","acquireLicensePage":"/videos/waterfall-huibang-falls-water-122459/","duration":"T0M15S","uploadDate":"2024-02-12T07:03:54.131Z","sourceOrganization":{"@type":"Organization","name":"Pixabay"}}, {"@context":"https://schema.org","@type":"VideoObject","contentUrl":"https://cdn.pixabay.com/vimeo/135882534/mont-royal-292.mp4?width=480&hash=c0c00280c94ab8cbd0071515a5d6a69540f34ed9","thumbnailUrl":"https://i.vimeocdn.com/video/530180624-8fe325bec7f770df99a5583b584949543c85f078b31d8daca60a2c43f20a0a32-d_640x360.jpg","name":"Mont Royal, Montreal, Canada","description":"Mont Royal, Montreal, Canada, City, Park, Buildings, People","license":"https://pixabay.com/service/license-summary/","acquireLicensePage":"/videos/mont-royal-montreal-canada-city-292/","duration":"T0M31S","uploadDate":"2024-02-12T07:03:54.132Z","sourceOrganization":{"@type":"Organization","name":"Pixabay"}}, {"@context":"https://schema.org","@type":"VideoObject","contentUrl":"https://cdn.pixabay.com/vimeo/573481981/vampire-80856.mp4?width=640&hash=bfb7e301982cbcae6ceb989b247e6cff350ad726","thumbnailUrl":"https://i.vimeocdn.com/video/1186010292-e74ea63174fabac20bdc15eb71d205dabf2f7d6248b2a85c47683fd34e9ba2ff-d_640x360.jpg","name":"Vampire, Woman, Dracula","description":"Vampire, Woman, Dracula, Nosferatu, Transylvania","license":"https://pixabay.com/service/license-summary/","acquireLicensePage":"/videos/vampire-woman-dracula-nosferatu-80856/","duration":"T0M10S","uploadDate":"2024-02-12T07:03:54.133Z","sourceOrganization":{"@type":"Organization","name":"Pixabay"}}, {"@context":"https://schema.org","@type":"VideoObject","contentUrl":"https://cdn.pixabay.com/vimeo/477792771/construction-site-54559.mp4?width=640&hash=11123e788f7eabeb90743a60206399fdf08063ce","thumbnailUrl":"https://i.vimeocdn.com/video/992334949-3f4094f0b3c46d090c5701818166a20e7f1cc0fec8d0dbe737b1431711e2f649-d_640x360.jpg","name":"Construction Site","description":"Construction Site, Construction Work, Construction Worker","license":"https://pixabay.com/service/license-summary/","acquireLicensePage":"/videos/construction-site-construction-work-54559/","duration":"T0M38S","uploadDate":"2024-02-12T07:03:54.134Z","sourceOrganization":{"@type":"Organization","name":"Pixabay"}}, {"@context":"https://schema.org","@type":"VideoObject","contentUrl":"https://cdn.pixabay.com/vimeo/657132302/thanks-100081.mp4?width=640&hash=b2b463df30f894fc96c0d767b55e1f2a4614ac8f","thumbnailUrl":"https://i.vimeocdn.com/video/1326602057-dd266fb9d1885bd5913a1802e928d6a0aed7acef439d95ea4c75494e28d64998-d_640x360.jpg","name":"Thanks, Thanks A Lot","description":"Thanks, Thanks A Lot, Thank You, Thank You Animation","license":"https://pixabay.com/service/license-summary/","acquireLicensePage":"/videos/thanks-thanks-a-lot-thank-you-100081/","duration":"T0M6S","uploadDate":"2024-02-12T07:03:54.135Z","sourceOrganization":{"@type":"Organization","name":"Pixabay"}}, {"@context":"https://schema.org","@type":"VideoObject","contentUrl":"https://cdn.pixabay.com/vimeo/552602449/common-merganser-74556.mp4?width=640&hash=517d05144b6eda2a0b50714721f72d2bb2cbdaba","thumbnailUrl":"https://i.vimeocdn.com/video/1141700469-4ff4c555d74366c619984da6932359705e531c318dc47d53af622886c04b1d67-d_640x360.jpg","name":"Common Merganser, Female","description":"Common Merganser, Female, The Water, Bank, Duck, Bird","license":"https://pixabay.com/service/license-summary/","acquireLicensePage":"/videos/common-merganser-female-the-water-74556/","duration":"T0M26S","uploadDate":"2024-02-12T07:03:54.136Z","sourceOrganization":{"@type":"Organization","name":"Pixabay"}}, {"@context":"https://schema.org","@type":"VideoObject","contentUrl":"https://cdn.pixabay.com/vimeo/754897645/bumblebee-132787.mp4?width=640&hash=65c2c63a3a4457624071c8b5fbf3b6c32660de4c","thumbnailUrl":"https://i.vimeocdn.com/video/1516678293-fa81cc60e83a9e566f9923d24ea84d266b187c3a34dd0363a2f5b096e94d490b-d_640x360.jpg","name":"Bumblebee, Insect","description":"Bumblebee, Insect, Flying Insect, Bramble","license":"https://pixabay.com/service/license-summary/","acquireLicensePage":"/videos/bumblebee-insect-flying-insect-132787/","duration":"T0M30S","uploadDate":"2024-02-12T07:03:54.138Z","sourceOrganization":{"@type":"Organization","name":"Pixabay"}}, {"@context":"https://schema.org","@type":"VideoObject","contentUrl":"https://cdn.pixabay.com/vimeo/714285545/mountains-118222.mp4?width=1280&hash=7a0310ca3bb4660800749f619b72bf3c9664c8b7","thumbnailUrl":"https://i.vimeocdn.com/video/1439689300-5f66fdcc470f6dac0845178302871dcb6b44bbad913f20853bb0b8544feb7dac-d_640x360.jpg","name":"Mountains, Zugspitze, Alps","description":"Mountains, Zugspitze, Alps, Clouds, Bavaria, Nature","license":"https://pixabay.com/service/license-summary/","acquireLicensePage":"/videos/mountains-zugspitze-alps-clouds-118222/","duration":"T0M13S","uploadDate":"2024-02-12T07:03:54.139Z","sourceOrganization":{"@type":"Organization","name":"Pixabay"}}, {"@context":"https://schema.org","@type":"VideoObject","contentUrl":"https://cdn.pixabay.com/vimeo/182666898/teddy-bear-5089.mp4?width=640&hash=7cb423bfdbe86c92142f24850ec15feb06c3ba91","thumbnailUrl":"https://i.vimeocdn.com/video/591641918-25c9141aa8b446e4d56b8b5c2a47d1320a8c7230328475277f1a63602b2af8be-d_640x360.jpg","name":"Teddy Bear, Toys, Kids","description":"Teddy Bear, Toys, Kids, Stuffed, Background","license":"https://pixabay.com/service/license-summary/","acquireLicensePage":"/videos/teddy-bear-toys-kids-stuffed-5089/","duration":"T0M15S","uploadDate":"2024-02-12T07:03:54.140Z","sourceOrganization":{"@type":"Organization","name":"Pixabay"}}, {"@context":"https://schema.org","@type":"VideoObject","contentUrl":"https://cdn.pixabay.com/vimeo/344986260/insect-24724.mp4?width=1280&hash=df99fd349d0c956259cda8a9835c0efb2263fcac","thumbnailUrl":"https://i.vimeocdn.com/video/794629406-9cee6e0b275bbf593dd54b9d85ac0a8cf0de91f2e81f4ee9fe499b9ad1ef098a-d_640x360.jpg","name":"Insect, Green, Bug, Tech, Key","description":"Insect, Green, Bug, Tech, Key, Keyboard","license":"https://pixabay.com/service/license-summary/","acquireLicensePage":"/videos/insect-green-bug-tech-key-24724/","duration":"T0M11S","uploadDate":"2024-02-12T07:03:54.141Z","sourceOrganization":{"@type":"Organization","name":"Pixabay"}}, {"@context":"https://schema.org","@type":"VideoObject","contentUrl":"https://cdn.pixabay.com/vimeo/751934502/forest-131839.mp4?width=640&hash=44fee2a5b40c83b6457fd76cb0e7508492bcae35","thumbnailUrl":"https://i.vimeocdn.com/video/1511471613-123291e7cd9557391063fdcbbdbdaa1d5d3f85329a25f4d8d0029476481a39fb-d_640x360.jpg","name":"Forest, Trees, View, Beam","description":"Forest, Trees, View, Beam, Light, Nature","license":"https://pixabay.com/service/license-summary/","acquireLicensePage":"/videos/forest-trees-view-beam-light-131839/","duration":"T0M30S","uploadDate":"2024-02-12T07:03:54.142Z","sourceOrganization":{"@type":"Organization","name":"Pixabay"}}, {"@context":"https://schema.org","@type":"VideoObject","contentUrl":"https://cdn.pixabay.com/vimeo/345209547/algeria-24651.mp4?width=1280&hash=62230f9846a6b547d25228b18d63c50461d46340","thumbnailUrl":"https://i.vimeocdn.com/video/794916469-bf9b09ac7a04cdd3f74386eba9a9659f85b0c494ace71eaf59765e2b835701e3-d_640x360.jpg","name":"Algeria, Africa, Symbol, Flag","description":"Algeria, Africa, Symbol, Flag, National, Country, Wind","license":"https://pixabay.com/service/license-summary/","acquireLicensePage":"/videos/algeria-africa-symbol-flag-24651/","duration":"T0M20S","uploadDate":"2024-02-12T07:03:54.143Z","sourceOrganization":{"@type":"Organization","name":"Pixabay"}}, {"@context":"https://schema.org","@type":"VideoObject","contentUrl":"https://cdn.pixabay.com/vimeo/461241976/forest-50686.mp4?width=640&hash=2126c733c414ed60dda8582377ac4dea2679cb35","thumbnailUrl":"https://i.vimeocdn.com/video/963047354-9678af26b8d33b27e8bd5bf0fc2245bc903815cd9f54fd75129e63dc50f8803c-d_640x360.jpg","name":"Forest, Cliff, Rock, Hill","description":"Forest, Cliff, Rock, Hill, Nature, Hike, Environment","license":"https://pixabay.com/service/license-summary/","acquireLicensePage":"/videos/forest-cliff-rock-hill-nature-50686/","duration":"T0M31S","uploadDate":"2024-02-12T07:03:54.144Z","sourceOrganization":{"@type":"Organization","name":"Pixabay"}}, {"@context":"https://schema.org","@type":"VideoObject","contentUrl":"https://cdn.pixabay.com/vimeo/639372256/waterfall-93182.mp4?width=640&hash=4b6c388a85410a221a2e3fbdb505fec273124162","thumbnailUrl":"https://i.vimeocdn.com/video/1285725451-2f4a054ead9fc2fbacf955e23b29b63ea6067377b3c141374_640x360.jpg","name":"Waterfall, Water, River","description":"Waterfall, Water, River, Canyon, Valley, Nature, Beautiful","license":"https://pixabay.com/service/license-summary/","acquireLicensePage":"/videos/waterfall-water-river-canyon-93182/","duration":"T0M35S","uploadDate":"2024-02-12T07:03:54.145Z","sourceOrganization":{"@type":"Organization","name":"Pixabay"}}, {"@context":"https://schema.org","@type":"VideoObject","contentUrl":"https://cdn.pixabay.com/vimeo/549555789/river-73869.mp4?width=1280&hash=d3e2a59d37cbec494de5a6fad229ffada871350b","thumbnailUrl":"https://i.vimeocdn.com/video/1137800017-98ec6022f4703f3101a8ef80d5839d559b52a2d931e60556cf696bba04738f0c-d_640x360.jpg","name":"River, Land, Water, Nature","description":"River, Land, Water, Nature","license":"https://pixabay.com/service/license-summary/","acquireLicensePage":"/videos/river-land-water-nature-73869/","duration":"T0M49S","uploadDate":"2024-02-12T07:03:54.146Z","sourceOrganization":{"@type":"Organization","name":"Pixabay"}}, {"@context":"https://schema.org","@type":"VideoObject","contentUrl":"https://cdn.pixabay.com/vimeo/753435400/windmill-132317.mp4?width=1280&hash=b741d43392e1f6aba02ce182bc1e1ad99dbd054e","thumbnailUrl":"https://i.vimeocdn.com/video/1514106702-21cd88e9fff109c4ba11a41738c841489b7acf65f918caf1e591c341afa4d408-d_640x360.jpg","name":"Windmill, Field, Trees, Forest","description":"Windmill, Field, Trees, Forest, Nature, Landscape, Daylight","license":"https://pixabay.com/service/license-summary/","acquireLicensePage":"/videos/windmill-field-trees-forest-nature-132317/","duration":"T0M18S","uploadDate":"2024-02-12T07:03:54.147Z","sourceOrganization":{"@type":"Organization","name":"Pixabay"}}, {"@context":"https://schema.org","@type":"VideoObject","contentUrl":"https://cdn.pixabay.com/vimeo/727905660/road-123433.mp4?width=640&hash=5dafcb38f7b1bbc8ebab49e316270d44e140a4f3","thumbnailUrl":"https://i.vimeocdn.com/video/1465186402-97b3fe82ce243737deb944f23a13ed974af597e9fe5f63301b784a8de4263a0a-d_640x360.jpg","name":"Road, Highway, Car, Vehicle","description":"Road, Highway, Car, Vehicle, Mountains, Nature","license":"https://pixabay.com/service/license-summary/","acquireLicensePage":"/videos/road-highway-car-vehicle-mountains-123433/","duration":"T0M21S","uploadDate":"2024-02-12T07:03:54.149Z","sourceOrganization":{"@type":"Organization","name":"Pixabay"}}, {"@context":"https://schema.org","@type":"VideoObject","contentUrl":"https://cdn.pixabay.com/vimeo/540442470/bird-71717.mp4?width=640&hash=3458d0966103889cd1402d19e788ea9ceea335da","thumbnailUrl":"https://i.vimeocdn.com/video/1118711514-53575c3d7a4e2436c39b895fd0e96da0e6b64aa59bf7fe43b2cd3d4effb6372f-d_640x360.jpg","name":"Bird, Sea, Beach, Waves","description":"Bird, Sea, Beach, Waves, Common Tern, Storm, Water, Clouds","license":"https://pixabay.com/service/license-summary/","acquireLicensePage":"/videos/bird-sea-beach-waves-common-tern-71717/","duration":"T0M27S","uploadDate":"2024-02-12T07:03:54.150Z","sourceOrganization":{"@type":"Organization","name":"Pixabay"}}, {"@context":"https://schema.org","@type":"VideoObject","contentUrl":"https://cdn.pixabay.com/vimeo/504238965/trees-62466.mp4?width=640&hash=d90bc1910fe8e4f04a34694494887906dd57ba98","thumbnailUrl":"https://i.vimeocdn.com/video/1043443522-9e18cfa10061e95595dec051536cf52d98f357d2f618a37db45c9c964296974a-d_640x360.jpg","name":"Trees, Pine, Snow, Winter","description":"Trees, Pine, Snow, Winter, Nature, Cold, Snowfall","license":"https://pixabay.com/service/license-summary/","acquireLicensePage":"/videos/trees-pine-snow-winter-nature-62466/","duration":"T0M17S","uploadDate":"2024-02-12T07:03:54.151Z","sourceOrganization":{"@type":"Organization","name":"Pixabay"}}, {"@context":"https://schema.org","@type":"VideoObject","contentUrl":"https://cdn.pixabay.com/vimeo/483011928/rose-54928.mp4?width=640&hash=835b11dd7fb74fb56df2008d791eef31c07e96c3","thumbnailUrl":"https://i.vimeocdn.com/video/1001246785-be7439badbf6192404bce37c2ed9555d5b85227248519dc49384a5ca866b7240-d_640x360.jpg","name":"Rose, Love, Blossom, Bloom","description":"Rose, Love, Blossom, Bloom, Flowers, Petals, Garden, Flora","license":"https://pixabay.com/service/license-summary/","acquireLicensePage":"/videos/rose-love-blossom-bloom-flowers-54928/","duration":"T0M14S","uploadDate":"2024-02-12T07:03:54.152Z","sourceOrganization":{"@type":"Organization","name":"Pixabay"}}, {"@context":"https://schema.org","@type":"VideoObject","contentUrl":"https://cdn.pixabay.com/vimeo/374487099/balls-29226.mp4?width=640&hash=8ee96dd0e4975692ea8f4f62e022354f72055ec0","thumbnailUrl":"https://i.vimeocdn.com/video/832948650-135d4237834623109c09920b6ab1fd9777e82c369e37d8fce620c9db43514eb8-d_640x360.jpg","name":"Balls, Molecules, Atoms, Red","description":"Balls, Molecules, Atoms, Red, Blood, Black, Light","license":"https://pixabay.com/service/license-summary/","acquireLicensePage":"/videos/balls-molecules-atoms-red-blood-29226/","duration":"T0M5S","uploadDate":"2024-02-12T07:03:54.153Z","sourceOrganization":{"@type":"Organization","name":"Pixabay"}}, {"@context":"https://schema.org","@type":"VideoObject","contentUrl":"https://cdn.pixabay.com/vimeo/460412843/beach-50436.mp4?width=1292&hash=23bebd14bbb98986153ff64ebc69fe106ae5f71f","thumbnailUrl":"https://i.vimeocdn.com/video/961690444-00a98cb9908cfe388409be62efd1ddf99507e34e39f276fe6c03eb77447c8f52-d_640x360.jpg","name":"Beach, Boat, Coast, Ocean, Sea","description":"Beach, Boat, Coast, Ocean, Sea, Island, Nature","license":"https://pixabay.com/service/license-summary/","acquireLicensePage":"/videos/beach-boat-coast-ocean-sea-island-50436/","duration":"T0M8S","uploadDate":"2024-02-12T07:03:54.154Z","sourceOrganization":{"@type":"Organization","name":"Pixabay"}}, {"@context":"https://schema.org","@type":"VideoObject","contentUrl":"https://cdn.pixabay.com/vimeo/329691493/fast-camera-22638.mp4?width=640&hash=3d882748ab28c70e0976222e74663b2fd4dbf8ef","thumbnailUrl":"https://i.vimeocdn.com/video/774562578-9ed11b6acf4d5b739ea56555628831f15f9aff1e273780fcdb6ee2f3f5a14008-d_640x360.jpg","name":"Fast Camera, Bubbles, Soap","description":"Fast Camera, Bubbles, Soap, Blown, Highlights, Bright","license":"https://pixabay.com/service/license-summary/","acquireLicensePage":"/videos/fast-camera-bubbles-soap-blown-22638/","duration":"T0M25S","uploadDate":"2024-02-12T07:03:54.155Z","sourceOrganization":{"@type":"Organization","name":"Pixabay"}}, {"@context":"https://schema.org","@type":"VideoObject","contentUrl":"https://cdn.pixabay.com/vimeo/533334119/river-70082.mp4?width=960&hash=e3d0d92f56a1a40f3d5fc35e73e0a8e3eb0a7e57","thumbnailUrl":"https://i.vimeocdn.com/video/1104038133-b5073b08a5e40988818da278621a1541660e1cfd21fa8fe3e94d5435fd5b73af-d_640x360.jpg","name":"River, Lake, Mountains, Italy","description":"River, Lake, Mountains, Italy, Umbria, Lagodicorbara, Water","license":"https://pixabay.com/service/license-summary/","acquireLicensePage":"/videos/river-lake-mountains-italy-umbria-70082/","duration":"T1M10S","uploadDate":"2024-02-12T07:03:54.156Z","sourceOrganization":{"@type":"Organization","name":"Pixabay"}}, {"@context":"https://schema.org","@type":"VideoObject","contentUrl":"https://cdn.pixabay.com/vimeo/285736495/sunset-17852.mp4?width=640&hash=d96a32c748683abfbe47c9c01c4c54b0d2020a2c","thumbnailUrl":"https://i.vimeocdn.com/video/720471674-9e71e34aa6b785f9acf5bd1f1f644d895af35f4e672652f71cadd33a8d909076-d_640x360.jpg","name":"Sunset, Eventide, Afternoon","description":"Sunset, Eventide, Afternoon, Clouds, Tranquility, Twilight","license":"https://pixabay.com/service/license-summary/","acquireLicensePage":"/videos/sunset-eventide-afternoon-clouds-17852/","duration":"T0M11S","uploadDate":"2024-02-12T07:03:54.157Z","sourceOrganization":{"@type":"Organization","name":"Pixabay"}}, {"@context":"https://schema.org","@type":"VideoObject","contentUrl":"https://cdn.pixabay.com/vimeo/357839145/winter-26377.mp4?width=640&hash=066ff96abd05669b61a1223775fc3639eaa2cb4e","thumbnailUrl":"https://i.vimeocdn.com/video/811299612-06449455ae12d2bdccffbc6dd3cf050ead692d6724b39a063dcebb4917d04825-d_640x360.jpg","name":"Winter, Wind, Snow, Nature","description":"Winter, Wind, Snow, Nature, Cold, Dramatic, Cloudy, Quiet","license":"https://pixabay.com/service/license-summary/","acquireLicensePage":"/videos/winter-wind-snow-nature-cold-26377/","duration":"T0M7S","uploadDate":"2024-02-12T07:03:54.158Z","sourceOrganization":{"@type":"Organization","name":"Pixabay"}}, {"@context":"https://schema.org","@type":"VideoObject","contentUrl":"https://cdn.pixabay.com/vimeo/754950579/ocean-132836.mp4?width=640&hash=7cf36d3db9b92affd028c55cec8628311e5583d4","thumbnailUrl":"https://i.vimeocdn.com/video/1516783983-d008e055dc9b619a2a3caedefc848a14ba24b4cea11f5a1d9f06fbc10b10121a-d_640x360.jpg","name":"Ocean, Sunset, Sunrise, Water","description":"Ocean, Sunset, Sunrise, Water, Ocean Wave, Nature, Iceland","license":"https://pixabay.com/service/license-summary/","acquireLicensePage":"/videos/ocean-sunset-sunrise-water-132836/","duration":"T0M10S","uploadDate":"2024-02-12T07:03:54.159Z","sourceOrganization":{"@type":"Organization","name":"Pixabay"}}, {"@context":"https://schema.org","@type":"VideoObject","contentUrl":"https://cdn.pixabay.com/vimeo/351374178/race-25559.mp4?width=640&hash=200e55ac08c76192ddf22ec7e425b0eea4970150","thumbnailUrl":"https://i.vimeocdn.com/video/802946786-15ad4c7119e48c396636b66e38c32b1b48bd2ff0a0d0ac0b68e1e70ac69528aa-d_640x360.jpg","name":"Race, Luxury, Isolated, Car","description":"Race, Luxury, Isolated, Car, Transport, Transportation","license":"https://pixabay.com/service/license-summary/","acquireLicensePage":"/videos/race-luxury-isolated-car-transport-25559/","duration":"T0M15S","uploadDate":"2024-02-12T07:03:54.161Z","sourceOrganization":{"@type":"Organization","name":"Pixabay"}}, {"@context":"https://schema.org","@type":"VideoObject","contentUrl":"https://cdn.pixabay.com/vimeo/187058245/light-5872.mp4?width=640&hash=d5ce250188c241c028656cc1c9aa411ee6be1484","thumbnailUrl":"https://i.vimeocdn.com/video/596681815-36dd363c4064ea8fa1c0ca1170ba4de4a2e19f8902e54e47f6bf208d006f79ca-d_640x360.jpg","name":"Light, Abstract, Art","description":"Light, Abstract, Art, Flow Of Light, Meteoric Light, Lights","license":"https://pixabay.com/service/license-summary/","acquireLicensePage":"/videos/light-abstract-art-flow-of-light-5872/","duration":"T0M10S","uploadDate":"2024-02-12T07:03:54.162Z","sourceOrganization":{"@type":"Organization","name":"Pixabay"}}, {"@context":"https://schema.org","@type":"VideoObject","contentUrl":"https://cdn.pixabay.com/vimeo/718118068/rain-shower-119496.mp4?width=1280&hash=8ccc0c6d266eb7d3793b3df4f270a811634ab812","thumbnailUrl":"https://i.vimeocdn.com/video/1446869043-4788591dd1afbefbf93f88baeb8075f06c2fa8806b0e74bf653e33556f2355f1-d_640x360.jpg","name":"Rain Shower, Raindrop","description":"Rain Shower, Raindrop, Rainy Weather, Clouds, Precipitation","license":"https://pixabay.com/service/license-summary/","acquireLicensePage":"/videos/rain-shower-raindrop-rainy-weather-119496/","duration":"T0M31S","uploadDate":"2024-02-12T07:03:54.163Z","sourceOrganization":{"@type":"Organization","name":"Pixabay"}}, {"@context":"https://schema.org","@type":"VideoObject","contentUrl":"https://cdn.pixabay.com/vimeo/607855992/sunrise-88439.mp4?width=640&hash=0781e72894f878f937aab653614b9ab3e08f2683","thumbnailUrl":"https://i.vimeocdn.com/video/1244557602-b4bf76a402fefba603e0901ad957e36ee0bca177e999ac7ac8427b10553b512f-d_640x360.jpg","name":"Sunrise, Sunset, Seascape","description":"Sunrise, Sunset, Seascape, Nature, Cumulus, Clouds, Dramatic","license":"https://pixabay.com/service/license-summary/","acquireLicensePage":"/videos/sunrise-sunset-seascape-nature-88439/","duration":"T0M33S","uploadDate":"2024-02-12T07:03:54.164Z","sourceOrganization":{"@type":"Organization","name":"Pixabay"}}, {"@context":"https://schema.org","@type":"VideoObject","contentUrl":"https://cdn.pixabay.com/vimeo/584851690/lake-83759.mp4?width=1280&hash=9f92ee0de592909b347ca9e858dfdc00e6aede10","thumbnailUrl":"https://i.vimeocdn.com/video/1210384095-c03379581b78ca7c95668e56fb5f0bdba52f28d242827b1b0d5f7d3a2f2d1eed-d_640x360.jpg","name":"Lake, Flowers, Lotus","description":"Lake, Flowers, Lotus, Aquatic Plants, Blooming, Russia","license":"https://pixabay.com/service/license-summary/","acquireLicensePage":"/videos/lake-flowers-lotus-aquatic-plants-83759/","duration":"T0M11S","uploadDate":"2024-02-12T07:03:54.165Z","sourceOrganization":{"@type":"Organization","name":"Pixabay"}}]